satori_playbook_validator-3.7.20.dist-info/METADATA
satori_playbook_validator-3.7.20.dist-info/WHEEL
satori_playbook_validator-3.7.20.dist-info/entry_points.txt
satorici/validator/__init__.py
satorici/validator/_validator.py
satorici/validator/exceptions.py
satorici/validator/schemas/command.json
satorici/validator/schemas/import.json
satorici/validator/schemas/input.json
satorici/validator/schemas/settings.json
satorici/validator/schemas/test.json
satorici/validator/warnings.py
satori_playbook_validator-3.7.20.dist-info/RECORD
