Metadata-Version: 2.1
Name: satori-playbook-validator
Version: 3.7.20
Author-Email: Satori CI <info@satori-ci.com>
License: MIT
Requires-Python: >=3.9
Requires-Dist: fastjsonschema>=2.18.1
Requires-Dist: aws-cron-expression-validator>=1.1.6
